<annotation>
	<folder>final_data</folder>
	<filename>img471.jpg</filename>
	<path>C:\Users\lant\Desktop\illegal_poacher_detection\final_data\img471.jpg</path>
	<source>
		<database>Unknown</database>
	</source>
	<size>
		<width>640</width>
		<height>640</height>
		<depth>3</depth>
	</size>
	<segmented>0</segmented>
	<object>
		<name>poacher</name>
		<pose>Unspecified</pose>
		<truncated>0</truncated>
		<difficult>0</difficult>
		<bndbox>
			<xmin>354</xmin>
			<ymin>288</ymin>
			<xmax>545</xmax>
			<ymax>601</ymax>
		</bndbox>
	</object>
	<object>
		<name>gun</name>
		<pose>Unspecified</pose>
		<truncated>0</truncated>
		<difficult>0</difficult>
		<bndbox>
			<xmin>428</xmin>
			<ymin>257</ymin>
			<xmax>560</xmax>
			<ymax>589</ymax>
		</bndbox>
	</object>
</annotation>
